pyreaver/__init__.py
pyreaver/executor.py
pyreaver/models.py
pyreaver/reaver.py
pyreaver/wash.py
pyreaver-0.1.3.dist-info/WHEEL
pyreaver-0.1.3.dist-info/METADATA
pyreaver-0.1.3.dist-info/RECORD
