Metadata-Version: 2.1
Name: pyreaver
Version: 0.1.3
Summary: 
Home-page: UNKNOWN
License: UNKNOWN
Author: David Francos
Author-email: opensource@davidfrancos.net
Requires-Python: >=3.7,<4.0
Classifier: Programming Language :: Python :: 3
Classifier: Programming Language :: Python :: 3.7
Requires-Dist: async-timeout (>=3.0,<4.0)
Requires-Dist: docopt (>=0.6.2,<0.7.0)
Requires-Dist: parse (>=1.12,<2.0)
Requires-Dist: stringcase (>=1.2,<2.0)
